{
    "organization": "podman-container-tools",
    "repository": "buildah",
    "number": 5392,
    "type": "issue",
    "title": "SBOM: the Syft preset could use a more suitable set of catalogers",
    "state": "open",
    "labels": [
        "stale-issue"
    ],
    "user": "chmeliik",
    "body": "**Description**\n\nThe \"syft\" [SBOM preset](https://www.mankier.com/1/buildah-commit#--sbom) scans both the context directory and the rootfs as plain `dir:`s. Syft selects the default set of catalogers based on what it is scanning: https://github.com/anchore/syft?tab=readme-ov-file#package-cataloger-selection\n\nYou can see the list of catalogers enabled for directory scanning and image scanning with:\n\n```bash\nsyft cataloger list --select-catalogers directory\nsyft cataloger list --select-catalogers image\n```\n\nAnd the list of catalogers enabled only for image scanning:\n\n```bash\n$ syft cataloger list -o json | jq '.catalogers[] | select(.tags | contains([\"image\"])) | select(.tags | contains([\"directory\"]) | not) | .name' -r\ncargo-auditable-binary-cataloger\nconan-info-cataloger\njavascript-package-cataloger\nphp-composer-installed-cataloger\nr-package-cataloger\nruby-installed-gemspec-cataloger\n```\n\nIt would be suitable to use `--select-cataloggers image` when scanning the rootfs.",
    "comments": [
        {
            "user": "nalind",
            "body": "Sounds reasonable.  Is the default of \"--select-catalogers directory\" the best one for build context directories?"
        },
        {
            "user": "chmeliik",
            "body": "> Sounds reasonable. Is the default of \"--select-catalogers directory\" the best one for build context directories?\n\nYes, I think so"
        },
        {
            "user": "github-actions[bot]",
            "body": "A friendly reminder that this issue had no activity for 30 days."
        }
    ],
    "cross_references": []
}