{
    "organization": "podman-container-tools",
    "repository": "podman",
    "number": 9559,
    "title": "Missing swagger type for SpecGenerator expose attribute",
    "state": "closed",
    "labels": [
        "kind/bug",
        "locked - please file new issue/PR"
    ],
    "user": "TristanCacqueray",
    "body": "**Is this a BUG REPORT or FEATURE REQUEST? (leave only one on its own line)**\n\n/kind bug\n\n**Description**\n\nThe Swagger type for SpecGenerator.expose does not have a type.\n\n**Steps to reproduce the issue:**\n\n1. Lookup definition at https://docs.podman.io/en/latest/_static/api.html#operation/libpodCreateContainer\n\n**Describe the results you received:**\n\nThe expose attribute type is Any.\n\n**Describe the results you expected:**\n\nThe correct attribute type, e.g. `map of uint16 (port number) to a string`.",
    "comments": [
        {
            "user": "mheon",
            "body": "@jwhonce PTAL"
        },
        {
            "user": "github-actions[bot]",
            "body": "A friendly reminder that this issue had no activity for 30 days."
        },
        {
            "user": "rhatdan",
            "body": "@TristanCacqueray could you open a PR to fix?"
        },
        {
            "user": "TristanCacqueray",
            "body": "It seems like the issue is related to the `uint16` basic type for the key, but i can't find where or how to fix that."
        },
        {
            "user": "github-actions[bot]",
            "body": "A friendly reminder that this issue had no activity for 30 days."
        },
        {
            "user": "github-actions[bot]",
            "body": "A friendly reminder that this issue had no activity for 30 days."
        }
    ]
}