{
    "organization": "podman-container-tools",
    "repository": "podman",
    "number": 1257,
    "type": "pull_request",
    "title": "when searching, survive errors for multiple registries",
    "state": "closed",
    "labels": [
        "locked - please file new issue/PR"
    ],
    "user": "baude",
    "body": "when searching multiple registries for images, if we get an error on one\nof the searches, we should keep going and complete the search.  if there\nis only one search registry however, we will return an error.\n\nResolves: #1255\n\nSigned-off-by: baude <bbaude@redhat.com>",
    "comments": [
        {
            "user": "baude",
            "body": "lets merge this"
        },
        {
            "user": "mheon",
            "body": "Sure\nLGTM\n@rh-atomic-bot r+"
        },
        {
            "user": "mheon",
            "body": "I think we might need to get rh-atomic-bot added to the containers org, maybe?"
        },
        {
            "user": "rhatdan",
            "body": "@rh-atomic-bot r+"
        },
        {
            "user": "mheon",
            "body": "@rh-atomic-bot r+"
        },
        {
            "user": "rh-atomic-bot",
            "body": ":pushpin: Commit a04e7e1 has been approved by `mheon`\n\n<!-- @rh-atomic-bot r=mheon a04e7e150c18d489d08920078d9d37391399d6a8 -->"
        },
        {
            "user": "rh-atomic-bot",
            "body": ":hourglass: Testing commit a04e7e1 with merge 8f3621f..."
        },
        {
            "user": "mheon",
            "body": "I think I straight broke the papr tests by manually merging the systemd cgroups stuff"
        },
        {
            "user": "rh-atomic-bot",
            "body": ":broken_heart: Test failed - [status-papr](https://s3.amazonaws.com/aos-ci/ghprb/containers/libpod/8f3621f698c8a45202b235dcaaab033e1288dddc.1534193459903449600/index.html)"
        },
        {
            "user": "mheon",
            "body": "@rh-atomic-bot retry"
        },
        {
            "user": "rh-atomic-bot",
            "body": ":hourglass: Testing commit a04e7e1 with merge 5d7b31d..."
        },
        {
            "user": "rh-atomic-bot",
            "body": ":sunny: Test successful - [status-papr](https://s3.amazonaws.com/aos-ci/ghprb/containers/libpod/5d7b31da73bc3d9a3c0872fa912fef273b574e81.1534213410654316800/index.html)\nApproved by: mheon\nPushing 5d7b31da73bc3d9a3c0872fa912fef273b574e81 to master..."
        }
    ],
    "cross_references": []
}