{
    "organization": "podman-container-tools",
    "repository": "podman",
    "number": 1893,
    "type": "pull_request",
    "title": "Refactor CLI booleans to be consistent and defined behavior",
    "state": "closed",
    "labels": [
        "lgtm",
        "approved",
        "locked - please file new issue/PR"
    ],
    "user": "jwhonce",
    "body": "* Change all store_true or store_false to use store_bool.\n  New behavior documented in BooleanAction docstring.\n* Remove any extraneous code identified by pylint in files from above.\n\nFixes #1869\nFixes #1922\n\nSigned-off-by: Jhon Honce <jhonce@redhat.com>",
    "comments": [
        {
            "user": "jwhonce",
            "body": "@edsantiago PTAL"
        },
        {
            "user": "rhatdan",
            "body": "/approve"
        },
        {
            "user": "openshift-ci-robot",
            "body": "[APPROVALNOTIFIER] This PR is **APPROVED**\n\nThis pull-request has been approved by: *<a href=\"https://github.com/containers/libpod/pull/1893#issuecomment-443071538\" title=\"Approved\">rhatdan</a>*\n\nThe full list of commands accepted by this bot can be found [here](https://go.k8s.io/bot-commands).\n\nThe pull request process is described [here](https://git.k8s.io/community/contributors/guide/owners.md#the-code-review-process)\n\n<details >\nNeeds approval from an approver in each of these files:\n\n- ~~[OWNERS](https://github.com/containers/libpod/blob/master/OWNERS)~~ [rhatdan]\n\nApprovers can indicate their approval by writing `/approve` in a comment\nApprovers can cancel approval by writing `/approve cancel` in a comment\n</details>\n<!-- META={\"approvers\":[]} -->"
        },
        {
            "user": "rh-atomic-bot",
            "body": ":umbrella: The latest upstream changes (presumably #1894) made this pull request unmergeable. Please resolve the merge conflicts."
        },
        {
            "user": "edsantiago",
            "body": "I'd like to see my comments from yesterday and today addressed, but otherwise, this LGTM (and 'G' here stands for 'Great', not Good). Really nice work, Jhon."
        },
        {
            "user": "cevich",
            "body": "/lgtm"
        },
        {
            "user": "cevich",
            "body": "Oops, @jwhonce I didn't realize my /lgtm would cause the bot to merge.  I wasn't trying to disagree with @edsantiago 'I'd like to see my comments from yesterday and today addressed', his two little suggestions seemed helpful.  Can I open an issue on them or will you remember?"
        },
        {
            "user": "jwhonce",
            "body": "@cevich I'm already working on the next PR and will roll Ed's comments into that one.  With Ed's review, I realized I could delete the whole loop. :+1:   /cc @edsantiago "
        }
    ],
    "cross_references": [
        {
            "organization": "podman-container-tools",
            "repository": "podman",
            "number": 1894
        }
    ]
}