{
    "organization": "podman-container-tools",
    "repository": "podman",
    "number": 26229,
    "title": "Build for archive posted to podman unix socket fails (insufficient UIDs or GIDs available in user namespace)",
    "state": "closed",
    "labels": [
        "kind/bug",
        "locked - please file new issue/PR"
    ],
    "user": "robobario",
    "body": "### Issue Description\n\nHi! I'm working with a project that uses a maven plugin to execute a docker build ([fabric8io/docker-maven-plugin](https://dmp.fabric8.io/)) and I'm pointing it at a podman unix socket. The build fails on my machine with:\n\n```\n[INFO] --- docker:0.46.0:build (default) @ kroxylicious-app ---\n[INFO] Building tar: /home/robeyoun/development/upstream/kroxylicious/kroxylicious-app/target/docker/quay.io/kroxylicious/proxy/0.13.0-SNAPSHOT/tmp/docker-build.tar\n[INFO] DOCKER> [quay.io/kroxylicious/proxy:0.13.0-SNAPSHOT] \"pxy\": Created docker-build.tar in 1 second \n[ERROR] DOCKER> Unable to build image [quay.io/kroxylicious/proxy:0.13.0-SNAPSHOT] : Connection reset by peer [Connection reset by peer]\n```\n\nwhen it tries to POST an image-build to `/run/user/4210516/podman/podman.sock`\n\nI can see in the podman journalctl logs:\n\n```\nMay 29 10:48:43 robeyoun-thinkpadp16vgen1.rmtnz.csb podman[911361]: @ - - [29/May/2025:10:48:43 +1200] \"GET /version HTTP/1.1\" 200 1021 \"\" \"Apache-HttpClient/4.5.13 (Java/21.0.4)\"\nMay 29 10:48:44 robeyoun-thinkpadp16vgen1.rmtnz.csb podman[911361]: @ - - [29/May/2025:10:48:44 +1200] \"GET /v1.41/images/registry.access.redhat.com%2Fubi9%2Fubi-minimal%3A9.6-1747218906/json HTTP/1.1\" 200 3059 \"\" \"Apache-HttpClient/4.5.13 (Java/21.0.4)\"\nMay 29 10:48:44 robeyoun-thinkpadp16vgen1.rmtnz.csb podman[911361]: @ - - [29/May/2025:10:48:44 +1200] \"GET /v1.41/images/registry.access.redhat.com%2Fubi9%2Fubi-minimal%3A9.6-1747218906/json HTTP/1.1\" 200 3059 \"\" \"Apache-HttpClient/4.5.13 (Java/21.0.4)\"\nMay 29 10:48:44 robeyoun-thinkpadp16vgen1.rmtnz.csb podman[911361]: @ - - [29/May/2025:10:48:44 +1200] \"GET /v1.41/images/registry.access.redhat.com%2Fubi9%2Fubi-minimal%3A9.6-1747218906/json HTTP/1.1\" 200 3059 \"\" \"Apache-HttpClient/4.5.13 (Java/21.0.4)\"\nMay 29 10:48:44 robeyoun-thinkpadp16vgen1.rmtnz.csb podman[911361]: time=\"2025-05-29T10:48:44+12:00\" level=info msg=\"Request Failed(Not Found): failed to find image quay.io/kroxylicious/proxy:0.13.0-SNAPSHOT: quay.io/kroxylicious/proxy:0.13.0-SNAPSHOT: No such image\"\nMay 29 10:48:44 robeyoun-thinkpadp16vgen1.rmtnz.csb podman[911361]: @ - - [29/May/2025:10:48:44 +1200] \"GET /v1.41/images/quay.io%2Fkroxylicious%2Fproxy%3A0.13.0-SNAPSHOT/json HTTP/1.1\" 404 285 \"\" \"Apache-HttpClient/4.5.13 (Java/21.0.4)\"\nMay 29 10:48:44 robeyoun-thinkpadp16vgen1.rmtnz.csb podman[911361]: time=\"2025-05-29T10:48:44+12:00\" level=info msg=\"Request Failed(Internal Server Error): potentially insufficient UIDs or GIDs available in user namespace (requested 4210516:4210516 for /var/tmp/libpod_builder2552006587/build/proxy.dockerfile): Check /etc/subuid and /etc/subgid if configured locally and run \\\"podman system migrate\\\": lchown /var/tmp/libpod_builder2552006587/build/proxy.dockerfile: invalid argument\"\nMay 29 10:48:44 robeyoun-thinkpadp16vgen1.rmtnz.csb podman[911361]: @ - - [29/May/2025:10:48:44 +1200] \"POST /v1.41/build?buildargs=%7B%22KROXYLICIOUS_VERSION%22%3A%220.13.0-SNAPSHOT%22%7D&dockerfile=proxy.dockerfile&forcerm=1&nocache=0&squash=0&t=quay.io%2Fkroxylicious%2Fproxy%3A0.13.0-SNAPSHOT HTTP/1.1\" 500 385 \"\" \"Apache-HttpClient/4.5.13 (Java/21.0.4)\"\nMay 29 10:48:44 robeyoun-thinkpadp16vgen1.rmtnz.csb podman[911361]: time=\"2025-05-29T10:48:44+12:00\" level=info msg=\"Request Failed(Internal Server Error): potentially insufficient UIDs or GIDs available in user namespace (requested 4210516:4210516 for /var/tmp/libpod_builder973029959/build/proxy.dockerfile): Check /etc/subuid and /etc/subgid if configured locally and run \\\"podman system migrate\\\": lchown /var/tmp/libpod_builder973029959/build/proxy.dockerfile: invalid argument\"\nMay 29 10:48:44 robeyoun-thinkpadp16vgen1.rmtnz.csb podman[911361]: @ - - [29/May/2025:10:48:44 +1200] \"POST /v1.41/build?buildargs=%7B%22KROXYLICIOUS_VERSION%22%3A%220.13.0-SNAPSHOT%22%7D&dockerfile=proxy.dockerfile&forcerm=1&nocache=0&squash=0&t=quay.io%2Fkroxylicious%2Fproxy%3A0.13.0-SNAPSHOT HTTP/1.1\" 500 383 \"\" \"Apache-HttpClient/4.5.13 (Java/21.0.4)\"\nMay 29 10:48:45 robeyoun-thinkpadp16vgen1.rmtnz.csb podman[911361]: time=\"2025-05-29T10:48:45+12:00\" level=info msg=\"Request Failed(Internal Server Error): potentially insufficient UIDs or GIDs available in user namespace (requested 4210516:4210516 for /var/tmp/libpod_builder148438572/build/proxy.dockerfile): Check /etc/subuid and /etc/subgid if configured locally and run \\\"podman system migrate\\\": lchown /var/tmp/libpod_builder148438572/build/proxy.dockerfile: invalid argument\"\nMay 29 10:48:45 robeyoun-thinkpadp16vgen1.rmtnz.csb podman[911361]: @ - - [29/May/2025:10:48:45 +1200] \"POST /v1.41/build?buildargs=%7B%22KROXYLICIOUS_VERSION%22%3A%220.13.0-SNAPSHOT%22%7D&dockerfile=proxy.dockerfile&forcerm=1&nocache=0&squash=0&t=quay.io%2Fkroxylicious%2Fproxy%3A0.13.0-SNAPSHOT HTTP/1.1\" 500 383 \"\" \"Apache-HttpClient/4.5.13 (Java/21.0.4)\"\nMay 29 10:48:45 robeyoun-thinkpadp16vgen1.rmtnz.csb podman[911361]: time=\"2025-05-29T10:48:45+12:00\" level=info msg=\"Request Failed(Internal Server Error): potentially insufficient UIDs or GIDs available in user namespace (requested 4210516:4210516 for /var/tmp/libpod_builder3477251578/build/proxy.dockerfile): Check /etc/subuid and /etc/subgid if configured locally and run \\\"podman system migrate\\\": lchown /var/tmp/libpod_builder3477251578/build/proxy.dockerfile: invalid argument\"\nMay 29 10:48:45 robeyoun-thinkpadp16vgen1.rmtnz.csb podman[911361]: @ - - [29/May/2025:10:48:45 +1200] \"POST /v1.41/build?buildargs=%7B%22KROXYLICIOUS_VERSION%22%3A%220.13.0-SNAPSHOT%22%7D&dockerfile=proxy.dockerfile&forcerm=1&nocache=0&squash=0&t=quay.io%2Fkroxylicious%2Fproxy%3A0.13.0-SNAPSHOT HTTP/1.1\" 500 385 \"\" \"Apache-HttpClient/4.5.13 (Java/21.0.4)\"\n```\n\nAfter some playing around with a reproducer I think podman is unhappy that it's receiving a `tar` which contains files owned by my uid. Maybe this is working as intended? Keen to understand the failure in any case.\n\nThank you!\n\n### Steps to reproduce the issue\n\nSteps to reproduce the issue\n1.  ```shell\n    #!/bin/bash\n    DIR=\"$(mktemp -d)\"\n    mkdir \"${DIR}/image\"\n    echo 'FROM scratch' > \"${DIR}/image/Containerfile\"\n    tar -cvf \"${DIR}/build.tar\" -C \"${DIR}/image\" .\n    curl --unix-socket \"$(podman info --format '{{.Host.RemoteSocket.Path}}')\" 'http://v1.41/build?dockerfile=Containerfile' --data-binary @${DIR}/build.tar --header 'Content-type: application/x-tar' -v\n    ```\n\n### Describe the results you received\n\nDescribe the results you received:\n\n```\n*   Trying /run/user/4210516/podman/podman.sock:0...\n* Connected to v1.41 (/run/user/4210516/podman/podman.sock) port 0\n* using HTTP/1.x\n> POST /build?dockerfile=Containerfile HTTP/1.1\n> Host: v1.41\n> User-Agent: curl/8.11.1\n> Accept: */*\n> Content-type: application/x-tar\n> Content-Length: 10240\n> \n* upload completely sent off: 10240 bytes\n< HTTP/1.1 500 Internal Server Error\n< Api-Version: 1.41\n< Content-Type: application/json\n< Libpod-Api-Version: 5.5.0\n< Server: Libpod/5.5.0 (linux)\n< X-Reference-Id: 0xc000096000\n< Date: Thu, 29 May 2025 01:17:12 GMT\n< Content-Length: 377\n< \n{\"cause\":\"invalid argument\",\"message\":\"potentially insufficient UIDs or GIDs available in user namespace (requested 4210516:4210516 for /var/tmp/libpod_builder439104631/build/Containerfile): Check /etc/subuid and /etc/subgid if configured locally and run \\\"podman system migrate\\\": lchown /var/tmp/libpod_builder439104631/build/Containerfile: invalid argument\",\"response\":500}\n* Connection #0 to host v1.41 left intact\n```\n\n### Describe the results you expected\n\nthe image builds successfully:\n\nfor example if I set the owner/group on the contents of the tar to not be my user, like:\n\n```\n#!/bin/bash\n\nDIR=\"$(mktemp -d)\"\nmkdir \"${DIR}/image\"\necho 'FROM scratch' > \"${DIR}/image/Containerfile\"\ntar -cvf \"${DIR}/build.tar\" --owner=10000 --group=10000 -C \"${DIR}/image\" .\ncurl --unix-socket \"$(podman info --format '{{.Host.RemoteSocket.Path}}')\" 'http://v1.41/build?dockerfile=Containerfile' --data-binary @${DIR}/build.tar --header 'Content-type: application/x-tar' -v\n```\n\nthen the curl succeeds with:\n\n```\n*   Trying /run/user/4210516/podman/podman.sock:0...\n* Connected to v1.41 (/run/user/4210516/podman/podman.sock) port 0\n* using HTTP/1.x\n> POST /build?dockerfile=Containerfile HTTP/1.1\n> Host: v1.41\n> User-Agent: curl/8.11.1\n> Accept: */*\n> Content-type: application/x-tar\n> Content-Length: 10240\n> \n* upload completely sent off: 10240 bytes\n< HTTP/1.1 200 OK\n< Api-Version: 1.41\n< Content-Type: application/json\n< Libpod-Api-Version: 5.5.0\n< Server: Libpod/5.5.0 (linux)\n< X-Reference-Id: 0xc000b002e8\n< Date: Thu, 29 May 2025 01:20:13 GMT\n< Transfer-Encoding: chunked\n< \n{\"stream\":\"STEP 1/1: FROM scratch\\n\"}\n{\"stream\":\"COMMIT\\n\"}\n{\"stream\":\"--\\u003e 5b1636a4f388\\n\"}\n{\"stream\":\"5b1636a4f38835f271a96a4bb0ab06a590745c9fa0f4fd7233baa5f7ceaaf0f7\\n\"}\n{\"aux\":{\"ID\":\"sha256:5b1636a4f38835f271a96a4bb0ab06a590745c9fa0f4fd7233baa5f7ceaaf0f7\"}}\n{\"stream\":\"Successfully built 5b1636a4f388\\n\"}\n* Connection #0 to host v1.41 left intact\n```\n\n### podman info output\n\n```yaml\nhost:\n  arch: amd64\n  buildahVersion: 1.40.0\n  cgroupControllers:\n  - cpu\n  - io\n  - memory\n  - pids\n  cgroupManager: systemd\n  cgroupVersion: v2\n  conmon:\n    package: conmon-2.1.13-1.fc42.x86_64\n    path: /usr/bin/conmon\n    version: 'conmon version 2.1.13, commit: '\n  cpuUtilization:\n    idlePercent: 95.49\n    systemPercent: 0.7\n    userPercent: 3.8\n  cpus: 16\n  databaseBackend: sqlite\n  distribution:\n    distribution: fedora\n    variant: workstation\n    version: \"42\"\n  eventLogger: journald\n  freeLocks: 2002\n  hostname: robeyoun-thinkpadp16vgen1.rmtnz.csb\n  idMappings:\n    gidmap:\n    - container_id: 0\n      host_id: 4210516\n      size: 1\n    - container_id: 1\n      host_id: 10000\n      size: 75536\n    uidmap:\n    - container_id: 0\n      host_id: 4210516\n      size: 1\n    - container_id: 1\n      host_id: 10000\n      size: 75536\n  kernel: 6.14.6-300.fc42.x86_64\n  linkmode: dynamic\n  logDriver: journald\n  memFree: 10378616832\n  memTotal: 65968975872\n  networkBackend: netavark\n  networkBackendInfo:\n    backend: netavark\n    dns:\n      package: aardvark-dns-1.15.0-1.fc42.x86_64\n      path: /usr/libexec/podman/aardvark-dns\n      version: aardvark-dns 1.15.0\n    package: netavark-1.15.0-1.fc42.x86_64\n    path: /usr/libexec/podman/netavark\n    version: netavark 1.15.0\n  ociRuntime:\n    name: crun\n    package: crun-1.21-1.fc42.x86_64\n    path: /usr/bin/crun\n    version: |-\n      crun version 1.21\n      commit: 10269840aa07fb7e6b7e1acff6198692d8ff5c88\n      rundir: /run/user/4210516/crun\n      spec: 1.0.0\n      +SYSTEMD +SELINUX +APPARMOR +CAP +SECCOMP +EBPF +CRIU +LIBKRUN +WASM:wasmedge +YAJL\n  os: linux\n  pasta:\n    executable: /usr/bin/pasta\n    package: passt-0^20250512.g8ec1341-1.fc42.x86_64\n    version: \"\"\n  remoteSocket:\n    exists: true\n    path: /run/user/4210516/podman/podman.sock\n  rootlessNetworkCmd: pasta\n  security:\n    apparmorEnabled: false\n    capabilities: CAP_CHOWN,CAP_DAC_OVERRIDE,CAP_FOWNER,CAP_FSETID,CAP_KILL,CAP_NET_BIND_SERVICE,CAP_SETFCAP,CAP_SETGID,CAP_SETPCAP,CAP_SETUID,CAP_SYS_CHROOT\n    rootless: true\n    seccompEnabled: true\n    seccompProfilePath: /usr/share/containers/seccomp.json\n    selinuxEnabled: true\n  serviceIsRemote: false\n  slirp4netns:\n    executable: /usr/bin/slirp4netns\n    package: slirp4netns-1.3.1-2.fc42.x86_64\n    version: |-\n      slirp4netns version 1.3.1\n      commit: e5e368c4f5db6ae75c2fce786e31eef9da6bf236\n      libslirp: 4.8.0\n      SLIRP_CONFIG_VERSION_MAX: 5\n      libseccomp: 2.5.5\n  swapFree: 8587964416\n  swapTotal: 8589930496\n  uptime: 75h 56m 43.00s (Approximately 3.12 days)\n  variant: \"\"\nplugins:\n  authorization: null\n  log:\n  - k8s-file\n  - none\n  - passthrough\n  - journald\n  network:\n  - bridge\n  - macvlan\n  - ipvlan\n  volume:\n  - local\nregistries:\n  docker.io:\n    Blocked: false\n    Insecure: false\n    Location: docker.io\n    MirrorByDigestOnly: false\n    Mirrors:\n    - Insecure: false\n      Location: mirror.gcr.io\n      PullFromMirror: \"\"\n    Prefix: docker.io\n    PullFromMirror: \"\"\n  search:\n  - registry.fedoraproject.org\n  - registry.access.redhat.com\n  - docker.io\nstore:\n  configFile: /home/robeyoun/.config/containers/storage.conf\n  containerStore:\n    number: 4\n    paused: 0\n    running: 1\n    stopped: 3\n  graphDriverName: overlay\n  graphOptions: {}\n  graphRoot: /home/robeyoun/.local/share/containers/storage\n  graphRootAllocated: 1022488809472\n  graphRootUsed: 255440625664\n  graphStatus:\n    Backing Filesystem: btrfs\n    Native Overlay Diff: \"true\"\n    Supports d_type: \"true\"\n    Supports shifting: \"false\"\n    Supports volatile: \"true\"\n    Using metacopy: \"false\"\n  imageCopyTmpDir: /var/tmp\n  imageStore:\n    number: 158\n  runRoot: /run/user/4210516/containers\n  transientStore: false\n  volumePath: /home/robeyoun/.local/share/containers/storage/volumes\nversion:\n  APIVersion: 5.5.0\n  BuildOrigin: Fedora Project\n  Built: 1747180800\n  BuiltTime: Wed May 14 12:00:00 2025\n  GitCommit: 0dbcb51477ee7ab8d3b47d30facf71fc38bb0c98\n  GoVersion: go1.24.3\n  Os: linux\n  OsArch: linux/amd64\n  Version: 5.5.0\n```\n\n### Podman in a container\n\nNo\n\n### Privileged Or Rootless\n\nRootless\n\n### Upstream Latest Release\n\nYes\n\n### Additional environment details\n\nAdditional environment details:\n\n```\ncat /etc/subuid\nrobeyoun:10000:75536\ncat /etc/subgid\nrobeyoun:10000:75536\necho $UID\n4210516\nuname -r\n6.14.6-300.fc42.x86_64\n```\n\n### Additional information\n\n_No response_",
    "comments": [
        {
            "user": "robobario",
            "body": "My workmate doesn't see this issue, difference being he has a UID of `1000` where I have this enormous one `4210516`."
        },
        {
            "user": "robobario",
            "body": "And now it's started working, and I don't know what's changed. I'll reopen if it happens again"
        },
        {
            "user": "robobario",
            "body": "Okay this cropped up again for our team and a workaround that seems to fix is allocating an enormous subuid range that can map my user id (and does not overlap with my userid)\n\n```\n$ cat /etc/subuid\nrobeyoun:4210517:4210517\n$ cat /etc/subgid\nrobeyoun:4210517:4210517\n```\n\nfollowed by a `podman system migrate`"
        }
    ]
}