{
    "organization": "podman-container-tools",
    "repository": "podman",
    "number": 4686,
    "type": "issue",
    "title": "1.7.0: Regression: source can't be a URL for COPY",
    "state": "closed",
    "labels": [
        "stale-issue",
        "locked - please file new issue/PR"
    ],
    "user": "edsantiago",
    "body": "```console\n# cat Dockerfile\nFROM alpine\nADD https://raw.githubusercontent.com/autotest/autotest-docker/master/LICENSE /LICENSE\n# podman build .\nSTEP 1: FROM alpine\nSTEP 2: ADD https://raw.githubusercontent.com/autotest/autotest-docker/master/LICENSE /LICENSE\nError: error building at STEP \"ADD https://raw.githubusercontent.com/autotest/autotest-docker/master/LICENSE /LICENSE\": source can't be a URL for COPY\n```\npodman-1.7.0-0.2.rc1.fc30 and .fc31\n\nWorks as expected on 1.6.2",
    "comments": [
        {
            "user": "rhatdan",
            "body": "I think this is a bug fix.  @TomSweeneyRedHat PTAL"
        },
        {
            "user": "TomSweeneyRedHat",
            "body": "Yep, we weren't matching Docker, now we are.  https://github.com/containers/buildah/pull/1977"
        },
        {
            "user": "edsantiago",
            "body": "Is that new docker behavior? Because docker 1.13 on RHEL7 allows it - that's why docker-autotest has an explicit test for it"
        },
        {
            "user": "TomSweeneyRedHat",
            "body": "I believe it's current Docker upstream behavior.  @QiWang19  worked on it."
        },
        {
            "user": "edsantiago",
            "body": "docker 19.03.5 allows it\n```console\n# docker build .\nSending build context to Docker daemon  2.048kB\nStep 1/2 : FROM alpine\nlatest: Pulling from library/alpine\n89d9c30c1d48: Pull complete\nDigest: sha256:c19173c5ada610a5989151111163d28a67368362762534d8a8121ce95cf2bd5a\nStatus: Downloaded newer image for alpine:latest\n ---> 965ea09ff2eb\nStep 2/2 : ADD https://raw.githubusercontent.com/autotest/autotest-docker/master/LICENSE /LICENSE\nDownloading  18.34kB\n ---> 9275b9a479aa\nSuccessfully built 9275b9a479aa\n```"
        },
        {
            "user": "edsantiago",
            "body": "I think this is due to [confusion between COPY and ADD](https://stackoverflow.com/questions/24958140/what-is-the-difference-between-the-copy-and-add-commands-in-a-dockerfile). COPY does not allow URLs; ADD does. I still believe this is an undesired regression."
        },
        {
            "user": "TomSweeneyRedHat",
            "body": "@edsantiago just to be clear in my noggin, COPY  with URL allowed in Docker RHEL-1.13.1 but not Docker upstream.  ADD with URL is allowed in both Dockr RHEL-1.13.1 and Docker upstream?"
        },
        {
            "user": "edsantiago",
            "body": "I don't know about Docker on RHEL: OpenStack is acting up and I can't get a virt. All I can say is that docker 19.03.5 allows `ADD URL`, and presumably so does every docker 1.13 in history since there's a docker-autotest for it. docker 19.03.5 chokes on `COPY URL`:\n```\nStep 2/2 : COPY https://raw.githubusercontent.com/autotest/autotest-docker/maste\nr/LICENSE /LICENSE\nCOPY failed: source can't be a URL for COPY\n```\nI have no way right now of knowing what docker-1.13 does with `COPY URL`."
        },
        {
            "user": "TomSweeneyRedHat",
            "body": "Thanks @edsantiago, I'll see if I can revert that ADD side of things."
        },
        {
            "user": "mheon",
            "body": "@edsantiago @TomSweeneyRedHat Should we hold 1.7.0 final release for a fix to this?"
        },
        {
            "user": "edsantiago",
            "body": "This is the sort of thing that is impossible to answer because it depends on use cases that (a) are entirely out of our control and, worse, (b) we have not the slightest clue about. There could be one person out there using this form, or one thousand. There is no way to know.\n\nGiven that this is a change since 1.6.2, and it breaks something that has \"worked\" for a long time, I would unfortunately say that this is a release blocker."
        },
        {
            "user": "edsantiago",
            "body": "Finally got a RHEL7 VM. docker-1.13.1-104.git4ef4b30.el7:\n```\nADD URL -> ok\nCOPY URL -> fails: Source can't be a URL for COPY\n```"
        },
        {
            "user": "TomSweeneyRedHat",
            "body": "@mheon PR WIP, if that goes well tonight/tomorrow, would like to squeeze into 1.7.0.  I think this might bite us otherwise."
        },
        {
            "user": "TomSweeneyRedHat",
            "body": "With PR https://github.com/containers/buildah/pull/2019 in play:\n```\n# buildah bud -t tom -f ~/Dockerfile.addurl .\nSTEP 1: FROM alpine\nSTEP 2: ADD https://raw.githubusercontent.com/autotest/autotest-docker/master/LICENSE /LICENSE\nSTEP 3: COMMIT tom\n\n```"
        },
        {
            "user": "TomSweeneyRedHat",
            "body": "btb, forgot to add, really, really great catch @edsantiago, TYVM!"
        },
        {
            "user": "github-actions[bot]",
            "body": "A friendly reminder that this issue had no activity for 30 days."
        },
        {
            "user": "edsantiago",
            "body": "This is fixed."
        }
    ],
    "cross_references": [
        {
            "organization": "podman-container-tools",
            "repository": "buildah",
            "number": 2019
        },
        {
            "organization": "podman-container-tools",
            "repository": "buildah",
            "number": 4173
        }
    ]
}