{
    "organization": "podman-container-tools",
    "repository": "podman",
    "number": 6839,
    "type": "issue",
    "title": "Rootless pods crash after start via systemd",
    "state": "closed",
    "labels": [
        "kind/bug",
        "locked - please file new issue/PR"
    ],
    "user": "0xb35c",
    "body": "**Is this a BUG REPORT or FEATURE REQUEST? (leave only one on its own line)**\n\n/kind bug\n\n**Description**\n\nI want to be able to start and stop rootless pods via systemd units. Currently we only have version 1.6.4 available so I can't use the better systemd support of v2 right now. (Not sure which version is currently available in the upstream RH repos, as v2 of podman is still somewhat young). Anyways, that's not the issue as far as I can tell, as I get the same behaviour on my fedora workstation with podman v2.0.0.\n\nSo I wrote a quite simple systemd unit to simply `podman play kube <podfile>` and `podman pod start <podname>`, as I want to make sure the pods are also started after the system is rebooted. If I run those commands directly on bash everything works fine.\nIf the pods are started via the unit, they seem to crash immediately in a way even podman doesn't notice. `podman ps -a` says everything is up and running, while it actually is not. After `podman ps -a --sync` podman will correctly notice that the containers are dead.\n\nIs there something I'm missing? I've seen from other issues, that \"User=\" in the systemd unit might cause issues, but as far as I understand it is more regarding the PIDFile, which I don't use here. (Been there, failed with that :/)\n\n**Steps to reproduce the issue:**\nPodfile (originally created via podman):\n```yml\napiVersion: v1\nkind: Pod\nmetadata:\n  creationTimestamp: \"2020-06-22T14:38:24Z\"\n  labels:\n    app: pac\n  name: pac-app\nspec:\n  containers:\n    - env:\n        - name: PATH\n          value: /usr/local/sbin:/usr/local/bin:/usr/sbin:/usr/bin:/sbin:/bin\n        - name: TERM\n          value: xterm\n        - name: HOSTNAME\n          value: pac-app\n        - name: container\n          value: oci\n      ports:\n        - containerPort: 9000\n          hostPort: 9000\n          protocol: TCP\n      image: our.internal.artifactory.host/path/to/pac-app:test\n      name: pac-app-container\n      resources: {}\n      securityContext:\n        allowPrivilegeEscalation: true\n        capabilities: {}\n        privileged: false\n        readOnlyRootFilesystem: false\n        runAsUser: 0\n      workingDir: /home/docker-user\nstatus: {}\n```\nSystemd unit:\n```\n[Unit]\nDescription=Podman pac-app.service\nDocumentation=man:podman-generate-systemd(1)\n\n[Service]\n# ignore result of play kube - that's just to initially create the pod if not existent\nExecStartPre=-/bin/podman play kube /path/to/pac-app.pod.yml\nExecStart=/bin/podman pod start pac-app\nExecStop=-/bin/podman pod stop -t 10 pac-app\nType=oneshot\nUser=docker-deploy\nTimeoutStartSec=60\nRemainAfterExit=yes\nKillMode=none\n\n[Install]\nWantedBy=multi-user.target\n```\n\n1. Place the podfile and systemd unit file\n2. `systemctl enable pac-app.service`\n3. `systemctl start pac-app.service`\n\n**Describe the results you received:**\n```\n> sudo systemctl start pac-app\n> podman ps -a\nCONTAINER ID  IMAGE                                                                                       COMMAND               CREATED        STATUS            PORTS                   NAMES\nbfb47fdf53f6  our.internal.artifactory.host/path/to/pac-app:test  /bin/sh -c php-fp...  5 seconds ago  Up 5 seconds ago  0.0.0.0:9000->9000/tcp  pac-app-container\n4010aeb6655d  our.internal.artifactory.host/path/to/pause:3.2                                                    5 seconds ago  Up 5 seconds ago  0.0.0.0:9000->9000/tcp  037268f26eae-infra\n> podman ps -a --sync\nERRO[0005] No exit file for container 4010aeb6655d820c4b888e06884be2d0a29e86cf0c2c270f3e2c4e1ce635792e found: timed out waiting for file /run/user/12502/libpod/tmp/exits/4010aeb6655d820c4b888e06884be2d0a29e86cf0c2c270f3e2c4e1ce635792e: internal libpod error \nERRO[0005] No exit file for container bfb47fdf53f61b574eaca85a66c9e0f3f7664971ca9dd7dd1611382083bb64fd found: timed out waiting for file /run/user/12502/libpod/tmp/exits/bfb47fdf53f61b574eaca85a66c9e0f3f7664971ca9dd7dd1611382083bb64fd: internal libpod error \nCONTAINER ID  IMAGE                                                                                       COMMAND               CREATED         STATUS                              PORTS                   NAMES\nbfb47fdf53f6  our.internal.artifactory.host/path/to/pac-app:test  /bin/sh -c php-fp...  14 seconds ago  Exited (-1) Less than a second ago  0.0.0.0:9000->9000/tcp  pac-app-container\n4010aeb6655d  our.internal.artifactory.host/path/to/pause:3.2                                                    14 seconds ago  Exited (-1) Less than a second ago  0.0.0.0:9000->9000/tcp  037268f26eae-infra\n```\n\n**Describe the results you expected:**\nThis is what i get, when i run podman on the shell:\n```\n> podman play kube /path/to/pac-app.pod.yml\nPod:\ne3e7d431cb653a4c01b842b8d001461ba93f96e237e5774613e346e0ff6009fb\nContainer:\n033a8eead8c73cdefd2898ab8b80952afe67e9d5d5c28e139087226e57ac5a1f\n> podman ps -a --sync\nCONTAINER ID  IMAGE                                                                                       COMMAND               CREATED         STATUS            PORTS                   NAMES\n033a8eead8c7  our.internal.artifactory.host/path/to/pac-app:test  /bin/sh -c php-fp...  8 seconds ago   Up 8 seconds ago  0.0.0.0:9000->9000/tcp  pac-app-container\ned57f2fb03c5  our.internal.artifactory.host/path/to/pause:3.2                                                    22 seconds ago  Up 8 seconds ago  0.0.0.0:9000->9000/tcp  e3e7d431cb65-infra\n\n```\n\n\n\n**Additional information you deem important (e.g. issue happens only occasionally):**\nI also tried `Type=simple` in the unit file. That results in only having the infra container setup and running. The \"real\" container isn't even created.\n\n**Output of `podman version`:**\n\n```\npodman version 1.6.4\n```\n\n**Output of `podman info --debug`:**\n\n```\ndebug:\n  compiler: gc\n  git commit: \"\"\n  go version: go1.12.12\n  podman version: 1.6.4\nhost:\n  BuildahVersion: 1.12.0-dev\n  CgroupVersion: v1\n  Conmon:\n    package: conmon-2.0.15-1.el7_8.x86_64\n    path: /usr/bin/conmon\n    version: 'conmon version 2.0.15, commit: 372b4a12f1c2df4f70c280d41173b60acd3f1260'\n  Distribution:\n    distribution: '\"rhel\"'\n    version: \"7.8\"\n  IDMappings:\n    gidmap:\n    - container_id: 0\n      host_id: 12502\n      size: 1\n    - container_id: 1\n      host_id: 1214112\n      size: 65536\n    uidmap:\n    - container_id: 0\n      host_id: 12502\n      size: 1\n    - container_id: 1\n      host_id: 1214112\n      size: 65536\n  MemFree: 515940352\n  MemTotal: 16637501440\n  OCIRuntime:\n    name: runc\n    package: runc-1.0.0-67.rc10.el7_8.x86_64\n    path: /usr/bin/runc\n    version: 'runc version spec: 1.0.1-dev'\n  SwapFree: 3853512704\n  SwapTotal: 4294963200\n  arch: amd64\n  cpus: 6\n  eventlogger: file\n  hostname: lxneocidservices.schmid.local\n  kernel: 3.10.0-1127.13.1.el7.x86_64\n  os: linux\n  rootless: true\n  slirp4netns:\n    Executable: /bin/slirp4netns\n    Package: slirp4netns-0.4.3-4.el7_8.x86_64\n    Version: |-\n      slirp4netns version 0.4.3\n      commit: 2244b9b6461afeccad1678fac3d6e478c28b4ad6\n  uptime: 162h 49m 36.61s (Approximately 6.75 days)\nregistries:\n  blocked: null\n  insecure: null\n  search:\n  - docker.lxecartifactory.schmid.local\nstore:\n  ConfigFile: /home/docker-deploy/.config/containers/storage.conf\n  ContainerStore:\n    number: 2\n  GraphDriverName: overlay\n  GraphOptions:\n    overlay.mount_program:\n      Executable: /usr/bin/fuse-overlayfs\n      Package: fuse-overlayfs-0.7.2-6.el7_8.x86_64\n      Version: |-\n        fuse-overlayfs: version 0.7.2\n        FUSE library version 3.6.1\n        using FUSE kernel interface version 7.29\n  GraphRoot: /home/docker-deploy/.local/share/containers/storage\n  GraphStatus:\n    Backing Filesystem: xfs\n    Native Overlay Diff: \"false\"\n    Supports d_type: \"true\"\n    Using metacopy: \"false\"\n  ImageStore:\n    number: 3\n  RunRoot: /run/user/12502/containers\n  VolumePath: /home/docker-deploy/.local/share/containers/storage/volumes\n```\n\n**Package info (e.g. output of `rpm -q podman` or `apt list podman`):**\n\n```\npodman-1.6.4-18.el7_8.x86_64\n```\n\n**Additional environment details (AWS, VirtualBox, physical, etc.):**\nWhere running on virtualized (via VMWare) Red Hat Enterprise Linux Server release 7.8 (Maipo) boxes in our own data center",
    "comments": [
        {
            "user": "0xb35c",
            "body": "I found a workaround for the issue:\nIf I place the required commands in a shell script file and call that from the unit file, everything works as inspected.\nStill this doesn't fix the issue itself."
        },
        {
            "user": "vrothberg",
            "body": "Thanks for reaching out, @0xb35c!\n\nCan you share the output of `systemctl status`? I suspect that `oneshot` is a problem. Could you try setting it to `type=Forking`?"
        },
        {
            "user": "0xb35c",
            "body": "Hi,\n\nyeah sure. `systemctl status` with `Type=oneshot`:\n```\nsystemctl status pac-app\n● pac-app.service - Podman pac-app.service\n   Loaded: loaded (/usr/lib/systemd/system/pac-app.service; enabled; vendor preset: disabled)\n   Active: failed (Result: exit-code) since Thu 2020-07-02 13:16:28 CEST; 45s ago\n     Docs: man:podman-generate-systemd(1)\n  Process: 127551 ExecStart=/bin/pod start pac-app (code=exited, status=203/EXEC)\n  Process: 127187 ExecStartPre=/bin/podman play kube /path/to/pac-app.pod.yml (code=exited, status=0/SUCCESS)\n Main PID: 127551 (code=exited, status=203/EXEC)\n\nJul 02 13:16:17 podmanmachine.local podman[127187]: Writing manifest to image destination\nJul 02 13:16:17 podmanmachine.local podman[127187]: Storing signatures\nJul 02 13:16:28 podmanmachine.local podman[127187]: Pod:\nJul 02 13:16:28 podmanmachine.local podman[127187]: 22ccda935d2d32fd23b51d5166591270786ed195f7d2e8b447aef9e3447b5d32\nJul 02 13:16:28 podmanmachine.local podman[127187]: Container:\nJul 02 13:16:28 podmanmachine.local podman[127187]: 7287a3dfef85fabb83d2be49445e63b8985c4a27da6c0ab30d9c2d15cdbe45ed\nJul 02 13:16:28 podmanmachine.local systemd[1]: pac-app.service: main process exited, code=exited, status=203/EXEC\nJul 02 13:16:29 podmanmachine.local systemd[1]: Failed to start Podman pac-app.service.\nJul 02 13:16:29 podmanmachine.local systemd[1]: Unit pac-app.service entered failed state.\nJul 02 13:16:29 podmanmachine.local systemd[1]: pac-app.service failed.\n```\nIt's strange right now, as I didn't get errors before and I'm not sure what I changed that produces the error now. Still podman needs to sync first before it knows, that the containers are dead.\n\n\nAnd here `systemctl status` with `Type=forking`:\n```\nsystemctl status pac-app\n● pac-app.service - Podman pac-app.service\n   Loaded: loaded (/usr/lib/systemd/system/pac-app.service; enabled; vendor preset: disabled)\n   Active: failed (Result: exit-code) since Thu 2020-07-02 13:26:15 CEST; 30s ago\n     Docs: man:podman-generate-systemd(1)\n  Process: 1708 ExecStart=/bin/pod start pac-app (code=exited, status=203/EXEC)\n  Process: 1267 ExecStartPre=/bin/podman play kube /path/to/pac-app.pod.yml (code=exited, status=0/SUCCESS)\n Main PID: 130234 (code=exited, status=203/EXEC)\n\nJul 02 13:26:03 podmanmachine.local podman[1267]: Writing manifest to image destination\nJul 02 13:26:03 podmanmachine.local podman[1267]: Storing signatures\nJul 02 13:26:15 podmanmachine.local podman[1267]: Pod:\nJul 02 13:26:15 podmanmachine.local podman[1267]: 033e37ebf07284e4003aedcb16db7129ad32e87dfe312fab89e2e078cfe80a05\nJul 02 13:26:15 podmanmachine.local podman[1267]: Container:\nJul 02 13:26:15 podmanmachine.local podman[1267]: 11e045fe26926a156c50371eff2ca4cb794daba8f64fb85423ff0d425c4cd6cc\nJul 02 13:26:15 podmanmachine.local systemd[1]: pac-app.service: control process exited, code=exited status=203\nJul 02 13:26:15 podmanmachine.local systemd[1]: Failed to start Podman pac-app.service.\nJul 02 13:26:15 podmanmachine.local systemd[1]: Unit pac-app.service entered failed state.\nJul 02 13:26:15 podmanmachine.local systemd[1]: pac-app.service failed.\n```\npodman shows the same behaviour regarding its dead containers.\n\nDoes `Type=forking` make sense here? If I understand correctly this tells systemd to watch any forking process starting from the given ExecStart-command? (And fail/restart if this process exits?) Also I assumed that `Type=oneshot` means that systemd should just run that command and don't care about what happens then.\n\nIf you like, I can post the debug output for the systemd startup. Though it didn't seem to have any critical issues, as the containers seem to start at some point."
        },
        {
            "user": "0xb35c",
            "body": "Hi @vrothberg,\n\ndo you have any updates on this issue? :)\n\nThanks"
        },
        {
            "user": "vrothberg",
            "body": "Thanks for the ping! Apologies, I got pulled into other issues. I will have a look tomorrow."
        },
        {
            "user": "vrothberg",
            "body": "@0xb35c ... one last try: can you check with `type=simple`?\n\nWe didn't imagine `play kube` to be used in a systemd unit. With v2.0, `podman generate systemd` supports the `--new` flag also for pods, which may be something more reliable for your use case. However, v1.6.4 is too old to properly support these new features.\n\nIt looks like `oneshot` is shooting down the containers."
        },
        {
            "user": "limburgher",
            "body": "I think this is related: I'm on Fedora 32, podman 2.0.2.  I used generate to create a unit file for a pod. Systemd (245.6) won's start it: Service has more than one ExecStart= setting, which is only allowed for Type=oneshot services. Refusing.\n\noneshot fails as well: Unit container-7634fa278c8aa456da4354b6d7e0f39b11146db3f83ca019c21046c958b681e7.service not found."
        },
        {
            "user": "vrothberg",
            "body": "> I think this is related: I'm on Fedora 32, podman 2.0.2. I used generate to create a unit file for a pod. Systemd (245.6) won's start it: Service has more than one ExecStart= setting, which is only allowed for Type=oneshot services. Refusing.\n\nThat sounds like a red herring. Systemd happily eats multiple `ExecStarts`s for non-oneshot types of services. The generated unit files are of type=forking and they don't error. I just verified on workstation, also with F32, Podman v2.0.2 and systemd 245.6.\n\n"
        },
        {
            "user": "limburgher",
            "body": "The generated unit file was type=forking and do error, that's why I tried oneshot at all.\n\nFailed to start podman-esrapps.service: Unit podman-esrapps.service has a bad unit file setting.\nSee system logs and 'systemctl status podman-esrapps.service' for details.\n\njournalctl:\n\npodman-esrapps.service: Service has more than one ExecStart= setting, which is only allowed for Type=oneshot services. Refusing.\n[podman-esrapps.service.txt](https://github.com/containers/podman/files/4972065/podman-esrapps.service.txt)\n"
        },
        {
            "user": "vrothberg",
            "body": "Can you share a reproducer?"
        },
        {
            "user": "limburgher",
            "body": "Yes. Previous comment. pod generated with:\n#!/bin/bash\npodman pod create --name esrapps -p 7070:8080\npodman create --name irc_bot --pod esrapps esrum.org:5000/esrum /root/irc_bot.py\npodman create --name storged --user storge --pod esrapps esrum.org:5000/esrum /usr/sbin/storged -p 8080\n"
        },
        {
            "user": "vrothberg",
            "body": "Thanks! Unfortunately esrum.org:5000/esrum requires authentication, so I can't reproduce."
        },
        {
            "user": "limburgher",
            "body": "Yes, it's a private repo. The image is built from Fedora 32 and includes some python modules and internal software. Do you have a working pod whose generated systemd file works that I could try?"
        },
        {
            "user": "vrothberg",
            "body": "Sure. Here's an example:\n``` \nuser $ podman pod create --name=test-pod\n48be223f565a3f09c90a262114ea1c8401d35a59d9a972e06a0612354465d2da\nuser $ podman create --name=test-ctr --pod=test-pod fedora sleep 42m\n324385804c2357969fba15ac5c21dd57a3fe32a256f3c1e4b41d95fb4ea9ab2c\nuser $ podman generate systemd --files test-pod\n/home/valentin/.config/systemd/user/pod-48be223f565a3f09c90a262114ea1c8401d35a59d9a972e06a0612354465d2da.service\n/home/valentin/.config/systemd/user/container-324385804c2357969fba15ac5c21dd57a3fe32a256f3c1e4b41d95fb4ea9ab2c.service\nuser $ systemctl --user daemon-reload\nuser $ systemctl --user start pod-48be223f565a3f09c90a262114ea1c8401d35a59d9a972e06a0612354465d2da.service \nuser $ podman ps\nCONTAINER ID  IMAGE                            COMMAND    CREATED         STATUS            PORTS   NAMES\n2a2d3fd3a28d  k8s.gcr.io/pause:3.2                        39 seconds ago  Up 6 seconds ago          48be223f565a-infra\n324385804c23  docker.io/library/fedora:latest  sleep 42m  29 seconds ago  Up 5 seconds ago          test-ctr\nuser $ systemctl --user status pod-48be223f565a3f09c90a262114ea1c8401d35a59d9a972e06a0612354465d2da.service \n● pod-48be223f565a3f09c90a262114ea1c8401d35a59d9a972e06a0612354465d2da.service - Podman pod-48be223f565a3f09c90a262114ea1c8401d35a59d9a972e06>\n     Loaded: loaded (/home/valentin/.config/systemd/user/pod-48be223f565a3f09c90a262114ea1c8401d35a59d9a972e06a0612354465d2da.service; disabl>\n     Active: active (running) since Fri 2020-07-24 15:30:50 CEST; 20s ago\n       Docs: man:podman-generate-systemd(1)\n    Process: 1599614 ExecStart=/usr/bin/podman start 2a2d3fd3a28d126675173522365521d7cfd8830eb82939269da3fbd617329210 (code=exited, status=0/>\n   Main PID: 1599709 (conmon)\n      Tasks: 4 (limit: 19009)\n     Memory: 3.9M\n        CPU: 389ms\n     CGroup: /user.slice/user-1000.slice/user@1000.service/pod-48be223f565a3f09c90a262114ea1c8401d35a59d9a972e06a0612354465d2da.service\n             ├─1599666 /usr/bin/fuse-overlayfs -o lowerdir=/home/valentin/.local/share/containers/storage/overlay/l/GGCV23ATQC5Y5N3UCACXAS7BK>\n             ├─1599670 /usr/bin/slirp4netns --disable-host-loopback --mtu 65520 --enable-sandbox --enable-seccomp -c -e 3 -r 4 --netns-type=p>\n             └─1599709 /usr/bin/conmon --api-version 1 -c 2a2d3fd3a28d126675173522365521d7cfd8830eb82939269da3fbd617329210 -u 2a2d3fd3a28d126>\n\nJul 24 15:30:50 nebuchadnezzar systemd[1123]: Starting Podman pod-48be223f565a3f09c90a262114ea1c8401d35a59d9a972e06a0612354465d2da.service...\nJul 24 15:30:50 nebuchadnezzar podman[1599614]: 2a2d3fd3a28d126675173522365521d7cfd8830eb82939269da3fbd617329210\nJul 24 15:30:50 nebuchadnezzar systemd[1123]: Started Podman pod-48be223f565a3f09c90a262114ea1c8401d35a59d9a972e06a0612354465d2da.service.\n```"
        },
        {
            "user": "vrothberg",
            "body": "Note, I am in `$HOME/.config/systemd/user/`."
        },
        {
            "user": "limburgher",
            "body": "I had installed my unit file to /etc/systemd/system/, run daemon-reload, and attempted systemctl start podman esrapps, as root. I had used podman generate systemd > podman-esrapps.service, as I had for individual containers. I see yours generates multiple unit files. I wasn't aware of the --files flag...I take it a single unit file is therefore not intended to work?\n"
        },
        {
            "user": "vrothberg",
            "body": "Entirely my fault of not reading carefully enough, apologies! The error message now makes much more sense to me. What the unit files have is one ExecStart but mulitple ExecStartPre.\n\n> I had installed my unit file to /etc/systemd/system/, run daemon-reload, and attempted systemctl start podman esrapps, as root. I had used podman generate systemd > podman-esrapps.service, as I had for individual containers. I see yours generates multiple unit files. I wasn't aware of the --files flag...I take it a single unit file is therefore not intended to work?\n\nUsing the printed output for a pod will not work, no. That includes multiple unit files. We ran with it for backward compat reasons as it works for a container."
        },
        {
            "user": "limburgher",
            "body": "Ahhh, ok. The multiple unit files work perfectly. Thank you!"
        },
        {
            "user": "0xb35c",
            "body": "Hey there,\n\nsorry for not getting back to this for so long. I was able to get back to this issue today and tried to reproduce the issue for myself and it seems systemd is working as expected for now.\nI'm not sure if it relates to the fact, that I enabled lingering (`loginctl --enable-linger <user>`), though I tried turning it off and it still works.\n\nAnyways: I'll close this issue.\n\nThanks for your support so far :)"
        },
        {
            "user": "Elrondo46",
            "body": "Same problem and it's a random problem, runs in Raspberry pi for aarch64 ARM"
        },
        {
            "user": "Elrondo46",
            "body": "Please reopen the bug"
        },
        {
            "user": "mheon",
            "body": "This issue is over two years old. Please file a new issue, as it's quite likely that the cause has changed."
        }
    ],
    "cross_references": []
}